robits/__init__.py
robits/agents/__init__.py
robits/agents/base_agent.py
robits/agents/mello_agent.py
robits/app/__init__.py
robits/app/extrinsics_app.py
robits/app/misc/slider_widget.py
robits/audio/__init__.py
robits/audio/audio.py
robits/audio/cache_utils.py
robits/audio/speech.py
robits/audio/utils.py
robits/cli/__init__.py
robits/cli/agents/mello_cli.py
robits/cli/base_cli.py
robits/cli/cli_options.py
robits/cli/cli_utils.py
robits/cli/commands/config_cli.py
robits/cli/commands/dataset_cli.py
robits/cli/commands/move_cli.py
robits/cli/commands/scene_visu.py
robits/cli/commands/service_cli.py
robits/cli/commands/speech_cli.py
robits/cli/devices/camera_cli.py
robits/cli/devices/gripper_cli.py
robits/cli/devices/panda_cli.py
robits/cli/devices/robot_cli.py
robits/cli/main.py
robits/core/__init__.py
robits/core/abc/__init__.py
robits/core/abc/audio.py
robits/core/abc/camera.py
robits/core/abc/control.py
robits/core/abc/gripper.py
robits/core/abc/robot.py
robits/core/abc/speech.py
robits/core/compat.py
robits/core/config.py
robits/core/config_manager.py
robits/core/data_model/__init__.py
robits/core/data_model/action.py
robits/core/data_model/camera_capture.py
robits/core/data_model/dataset.py
robits/core/factory.py
robits/core/utils.py
robits/dataset/__init__.py
robits/dataset/camera.py
robits/dataset/io/__init__.py
robits/dataset/io/reader.py
robits/dataset/io/recorder.py
robits/dataset/io/stats_writer.py
robits/dataset/io/writer.py
robits/dataset/robot.py
robits/real/__init__.py
robits/real/franka/__init__.py
robits/real/franka/control.py
robits/real/franka/franka_web_client.py
robits/real/franka/gripper.py
robits/real/franka/robot.py
robits/real/realsense_camera.py
robits/real/robotiq_gripper.py
robits/remote/__init__.py
robits/remote/client/__init__.py
robits/remote/client/camera.py
robits/remote/client/client_base.py
robits/remote/client/gripper.py
robits/remote/client/robot.py
robits/remote/server/__init__.py
robits/remote/server/camera.py
robits-0.6.0.dist-info/WHEEL
robits-0.6.0.dist-info/entry_points.txt
robits-0.6.0.dist-info/METADATA
robits-0.6.0.dist-info/RECORD
