Metadata-Version: 2.3
Name: robits
Version: 0.6.0
Summary: Lightweight, modular, and scalable software stack for AI-driven robotic manipulation.
Keywords: robotics,AI,manipulation,research,perception,control,simulation
Author: Markus Grotz
Author-email: Markus Grotz <grotz@uw.edu>
License: MIT License
Classifier: Development Status :: 4 - Beta
Classifier: Programming Language :: Python :: 3
Classifier: Programming Language :: Python :: 3.9
Classifier: Programming Language :: Python :: 3.10
Classifier: Programming Language :: Python :: 3.11
Classifier: Programming Language :: Python :: 3.12
Classifier: Operating System :: OS Independent
Classifier: Framework :: Robot Framework
Classifier: Topic :: Scientific/Engineering :: Artificial Intelligence
Classifier: Topic :: Scientific/Engineering
Classifier: Intended Audience :: Science/Research
Classifier: Intended Audience :: Developers
Classifier: Environment :: Console
Requires-Dist: numpy>=1.24
Requires-Dist: matplotlib>=3.7.5,<4.0.0
Requires-Dist: scipy>=1.13,<2.0.0
Requires-Dist: ipython>=8.0
Requires-Dist: rich-click>=1
Requires-Dist: click-prompt>=0.6.0
Requires-Dist: textual>=1.0.0,<2.0.0
Requires-Dist: textual-slider>=0.1.2,<0.2.0
Requires-Dist: open3d==0.18.* ; python_full_version < '3.10'
Requires-Dist: open3d>=0.18 ; python_full_version >= '3.10'
Requires-Dist: pyrobotiqgripper>=1.0.1 ; extra == 'all'
Requires-Dist: franky-panda ; platform_machine == 'x86_64' and extra == 'all'
Requires-Dist: pyrealsense2>=2.55.1,<3.0 ; python_full_version < '3.12' and platform_machine == 'x86_64' and extra == 'all'
Requires-Dist: pyrealsense2-beta==2.56.0.8430 ; python_full_version >= '3.12' and platform_machine == 'x86_64' and extra == 'all'
Requires-Dist: mujoco==3.3.7 ; python_full_version < '3.10' and extra == 'all'
Requires-Dist: mujoco>=3.3,<4.0 ; python_full_version >= '3.10' and extra == 'all'
Requires-Dist: robot-descriptions>=1.14.0,<2.0 ; extra == 'all'
Requires-Dist: dm-control>=1.0.30,<2.0 ; extra == 'all'
Requires-Dist: usd-core>=23.5.0 ; extra == 'all'
Requires-Dist: zmq ; extra == 'all'
Requires-Dist: pyzmq ; extra == 'all'
Requires-Dist: psutil ; extra == 'all'
Requires-Dist: openai>=1.64.0 ; extra == 'audio'
Requires-Dist: openai-whisper>=20240930 ; extra == 'audio'
Requires-Dist: sounddevice>=0.5.2 ; extra == 'audio'
Requires-Dist: sphinx ; extra == 'dev'
Requires-Dist: toml ; extra == 'dev'
Requires-Dist: myst-parser ; extra == 'dev'
Requires-Dist: sphinx-rtd-theme ; extra == 'dev'
Requires-Dist: sphinxcontrib-video ; extra == 'dev'
Requires-Dist: ruff ; extra == 'dev'
Requires-Dist: pyrobotiqgripper>=1.0.1 ; extra == 'real'
Requires-Dist: franky-panda ; platform_machine == 'x86_64' and extra == 'real'
Requires-Dist: pyrealsense2>=2.55.1,<3.0 ; python_full_version < '3.12' and platform_machine == 'x86_64' and extra == 'real'
Requires-Dist: pyrealsense2-beta==2.56.0.8430 ; python_full_version >= '3.12' and platform_machine == 'x86_64' and extra == 'real'
Requires-Dist: zmq ; extra == 'remote'
Requires-Dist: pyzmq ; extra == 'remote'
Requires-Dist: psutil ; extra == 'remote'
Requires-Dist: mujoco==3.3.7 ; python_full_version < '3.10' and extra == 'sim'
Requires-Dist: mujoco>=3.3,<4.0 ; python_full_version >= '3.10' and extra == 'sim'
Requires-Dist: robot-descriptions>=1.14.0,<2.0 ; extra == 'sim'
Requires-Dist: dm-control>=1.0.30,<2.0 ; extra == 'sim'
Requires-Dist: urx>=0.11.0 ; extra == 'ur'
Requires-Dist: usd-core>=23.5.0 ; extra == 'usd'
Requires-Dist: mujoco==3.3.7 ; python_full_version < '3.10' and extra == 'usd'
Requires-Dist: mujoco>=3.3,<4.0 ; python_full_version >= '3.10' and extra == 'usd'
Requires-Dist: robot-descriptions>=1.14.0,<2.0 ; extra == 'usd'
Requires-Dist: dm-control>=1.0.30,<2.0 ; extra == 'usd'
Requires-Dist: xarm-python-sdk>=1.15.3 ; extra == 'xarm'
Requires-Python: >=3.9, <3.13
Project-URL: documentation, https://robits.readthedocs.io/en/latest/
Project-URL: homepage, https://robits.ai
Project-URL: repository, https://github.com/markusgrotz/robits
Project-URL: tracker, https://github.com/markusgrotz/robits/issues
Provides-Extra: all
Provides-Extra: audio
Provides-Extra: dev
Provides-Extra: real
Provides-Extra: remote
Provides-Extra: sim
Provides-Extra: ur
Provides-Extra: usd
Provides-Extra: xarm
